tests/__init__.py
tests/compatibility_test.py
tests/conftest.py
tests/helpers.py
tests/server_test.py
tests/test_integration.py
tests/test_models.py
tests/test_server_api.py
tests/test_utils.py
orange_mcp_tavily-0.1.6.dist-info/LICENSE
orange_mcp_tavily-0.1.6.dist-info/METADATA
orange_mcp_tavily-0.1.6.dist-info/WHEEL
orange_mcp_tavily-0.1.6.dist-info/top_level.txt
orange_mcp_tavily-0.1.6.dist-info/RECORD
