Metadata-Version: 2.1
Name: orange-mcp-tavily
Version: 0.1.6
Summary: A Model Context Protocol server that provides AI-powered web search capabilities using Tavily's search API
Home-page: 
Author: orange
Author-email: support@orange.ai
License: MIT
Keywords: orange
Classifier: Programming Language :: Python :: 3
Classifier: License :: OSI Approved :: MIT License
Classifier: Operating System :: OS Independent
Requires-Python: >=3.6
License-File: LICENSE
Requires-Dist: mcp>=1.0.0
Requires-Dist: pydantic>=2.10.2
Requires-Dist: python-dotenv>=1.0.1
Requires-Dist: tavily-python>=0.5.0
Provides-Extra: test
Requires-Dist: pytest>=7.0.0; extra == "test"
Requires-Dist: pytest-asyncio>=0.23.0; extra == "test"
Requires-Dist: pytest-mock>=3.10.0; extra == "test"
Requires-Dist: pytest-cov>=4.1.0; extra == "test"
